glutamate/__init__.py
glutamate/__main__.py
glutamate/consts.py
glutamate/database.py
glutamate/datamodel.py
glutamate/dataset.py
glutamate/download.py
glutamate/inner_types.py
glutamate/py.typed
glutamate/utils.py
glutamate-0.0.1a7.dist-info/METADATA
glutamate-0.0.1a7.dist-info/WHEEL
glutamate-0.0.1a7.dist-info/entry_points.txt
glutamate-0.0.1a7.dist-info/top_level.txt
glutamate-0.0.1a7.dist-info/RECORD
