Metadata-Version: 2.1
Name: glutamate
Version: 0.0.1a7
Summary: Python library for querying and downloading posts from e621
Author-email: jorektheglitch <jorektheglitch@yandex.ru>
Project-URL: Homepage, https://github.com/jorektheglitch/glutamate/
Keywords: e621,glutamate
Classifier: Programming Language :: Python
Classifier: Programming Language :: Python :: 3
Classifier: Programming Language :: Python :: 3.10
Classifier: Programming Language :: Python :: 3.11
Classifier: Operating System :: OS Independent
Classifier: Typing :: Typed
Requires-Python: >=3.10
Requires-Dist: adaptix>=3.0.0a3
Requires-Dist: aiofiles>=23.1
Requires-Dist: aiohttp>=3.8
Requires-Dist: aiohttp-socks>=0.8
Requires-Dist: polars>=0.17
Requires-Dist: tqdm>=4.65
Provides-Extra: dev
Requires-Dist: mypy; extra == "dev"
